pyopt/__init__.py
pyopt/option.py
python_options-1.0.0.post4.dist-info/LICENSE
python_options-1.0.0.post4.dist-info/METADATA
python_options-1.0.0.post4.dist-info/WHEEL
python_options-1.0.0.post4.dist-info/top_level.txt
python_options-1.0.0.post4.dist-info/RECORD
