Metadata-Version: 2.1
Name: python-options
Version: 1.0.0.post4
Summary: Make python class with option base on property. Using build option for client like kafka, command option like ffmpeg.
Home-page: https://github.com/TinDang97/python-options
Author: tindang
Author-email: rainstone1029x@gmail.com
License: LICENSE
Keywords: option,pyopt,python-options
Platform: UNKNOWN
Requires-Python: >=3.6
